ragtester/__init__.py
ragtester/config.py
ragtester/error_handling.py
ragtester/exceptions.py
ragtester/install.py
ragtester/logging_utils.py
ragtester/tester.py
ragtester/types.py
ragtester/utils.py
ragtester/document_loader/__init__.py
ragtester/document_loader/base.py
ragtester/document_loader/random_page_loader.py
ragtester/document_loader/simple_loaders.py
ragtester/evaluator/__init__.py
ragtester/evaluator/base.py
ragtester/evaluator/metrics_judge.py
ragtester/llm/__init__.py
ragtester/llm/api_utils.py
ragtester/llm/base.py
ragtester/llm/health_check.py
ragtester/llm/logging_wrapper.py
ragtester/llm/providers.py
ragtester/llm/providers_01ai.py
ragtester/llm/providers_anthropic.py
ragtester/llm/providers_baidu.py
ragtester/llm/providers_bedrock.py
ragtester/llm/providers_cohere.py
ragtester/llm/providers_deepseek.py
ragtester/llm/providers_fireworks.py
ragtester/llm/providers_gemini.py
ragtester/llm/providers_grok.py
ragtester/llm/providers_huggingface.py
ragtester/llm/providers_local.py
ragtester/llm/providers_mistral.py
ragtester/llm/providers_moonshot.py
ragtester/llm/providers_ollama.py
ragtester/llm/providers_openai.py
ragtester/llm/providers_perplexity.py
ragtester/llm/providers_qwen.py
ragtester/llm/providers_reka.py
ragtester/llm/providers_together.py
ragtester/llm/providers_zhipu.py
ragtester/question_generator/__init__.py
ragtester/question_generator/base.py
ragtester/question_generator/generators.py
ragtester/rag_client/__init__.py
ragtester/rag_client/base.py
ragtester/rag_client/clients.py
ragtester/reporter/__init__.py
ragtester/reporter/reporter.py
ragtester-0.2.0.dist-info/licenses/LICENSE
ragtester-0.2.0.dist-info/METADATA
ragtester-0.2.0.dist-info/WHEEL
ragtester-0.2.0.dist-info/top_level.txt
ragtester-0.2.0.dist-info/RECORD
