Metadata-Version: 2.4
Name: ragtester
Version: 0.2.0
Summary: A comprehensive Python library for testing and evaluating Retrieval-Augmented Generation (RAG) systems with LLM-generated questions and automated evaluation metrics
Author-email: ABHILASH M S <abhilashms230@gmail.com>
License-Expression: Apache-2.0
Project-URL: Homepage, https://github.com/abhilashms230/ragtester
Project-URL: Bug Reports, https://github.com/abhilashms230/ragtester/issues
Project-URL: Source, https://github.com/abhilashms230/ragtester
Project-URL: Documentation, https://github.com/abhilashms230/ragtester#readme
Keywords: rag,evaluation,llm,testing,ai,retrieval-augmented-generation,nlp
Classifier: Development Status :: 4 - Beta
Classifier: Intended Audience :: Developers
Classifier: Intended Audience :: Science/Research
Classifier: Operating System :: OS Independent
Classifier: Programming Language :: Python :: 3
Classifier: Programming Language :: Python :: 3.9
Classifier: Programming Language :: Python :: 3.10
Classifier: Programming Language :: Python :: 3.11
Classifier: Programming Language :: Python :: 3.12
Classifier: Topic :: Scientific/Engineering :: Artificial Intelligence
Classifier: Topic :: Software Development :: Testing
Classifier: Topic :: Text Processing :: Linguistic
Requires-Python: >=3.9
License-File: LICENSE
Requires-Dist: PyMuPDF>=1.23.0
Requires-Dist: python-docx>=0.8.11
Requires-Dist: requests>=2.28.0
Provides-Extra: openai
Requires-Dist: openai>=1.0.0; extra == "openai"
Provides-Extra: anthropic
Requires-Dist: anthropic>=0.7.0; extra == "anthropic"
Provides-Extra: bedrock
Requires-Dist: boto3>=1.26.0; extra == "bedrock"
Provides-Extra: grok
Requires-Dist: requests>=2.28.0; extra == "grok"
Provides-Extra: gemini
Requires-Dist: google-generativeai>=0.3.0; extra == "gemini"
Provides-Extra: mistral
Requires-Dist: mistralai>=1.0.0; extra == "mistral"
Provides-Extra: cohere
Requires-Dist: cohere>=4.0.0; extra == "cohere"
Provides-Extra: huggingface
Requires-Dist: requests>=2.28.0; extra == "huggingface"
Provides-Extra: fireworks
Requires-Dist: requests>=2.28.0; extra == "fireworks"
Provides-Extra: together
Requires-Dist: requests>=2.28.0; extra == "together"
Provides-Extra: perplexity
Requires-Dist: requests>=2.28.0; extra == "perplexity"
Provides-Extra: deepseek
Requires-Dist: requests>=2.28.0; extra == "deepseek"
Provides-Extra: reka
Requires-Dist: requests>=2.28.0; extra == "reka"
Provides-Extra: qwen
Requires-Dist: requests>=2.28.0; extra == "qwen"
Provides-Extra: moonshot
Requires-Dist: requests>=2.28.0; extra == "moonshot"
Provides-Extra: zhipu
Requires-Dist: requests>=2.28.0; extra == "zhipu"
Provides-Extra: baidu
Requires-Dist: requests>=2.28.0; extra == "baidu"
Provides-Extra: zeroone
Requires-Dist: requests>=2.28.0; extra == "zeroone"
Provides-Extra: ollama
Requires-Dist: requests>=2.28.0; extra == "ollama"
Provides-Extra: local-transformers
Requires-Dist: transformers>=4.30.0; extra == "local-transformers"
Requires-Dist: torch>=2.0.0; extra == "local-transformers"
Provides-Extra: local-llama
Requires-Dist: llama-cpp-python>=0.2.0; extra == "local-llama"
Provides-Extra: data
Requires-Dist: numpy>=1.24.0; extra == "data"
Requires-Dist: pandas>=2.0.0; extra == "data"
Provides-Extra: dev
Requires-Dist: black>=23.0.0; extra == "dev"
Requires-Dist: flake8>=6.0.0; extra == "dev"
Requires-Dist: mypy>=1.0.0; extra == "dev"
Provides-Extra: all
Requires-Dist: openai>=1.0.0; extra == "all"
Requires-Dist: anthropic>=0.7.0; extra == "all"
Requires-Dist: boto3>=1.26.0; extra == "all"
Requires-Dist: google-generativeai>=0.3.0; extra == "all"
Requires-Dist: mistralai>=1.0.0; extra == "all"
Requires-Dist: cohere>=4.0.0; extra == "all"
Requires-Dist: transformers>=4.30.0; extra == "all"
Requires-Dist: torch>=2.0.0; extra == "all"
Requires-Dist: llama-cpp-python>=0.2.0; extra == "all"
Requires-Dist: numpy>=1.24.0; extra == "all"
Requires-Dist: pandas>=2.0.0; extra == "all"
Requires-Dist: black>=23.0.0; extra == "all"
Requires-Dist: flake8>=6.0.0; extra == "all"
Requires-Dist: mypy>=1.0.0; extra == "all"
Dynamic: license-file
